{"S1_summer_1886_2": {"retry": 0, "task_def": {"action": "export_single_feature", "id": "S1_summer_1886_2", "kwargs": {"roi": [[[12.967610647965339, 5.388910789369063], [13.408718167198883, 5.388910789369063], [13.408718167198883, 5.801633723602107], [12.967610647965339, 5.801633723602107], [12.967610647965339, 5.388910789369063]]], "export_params": {"bucket": "sentinel2", "resolution": 10, "filename": "summer_1886_2", "dest_path": "S1/summer/1886/summer_1886_2"}, "sensor": {"name": "COPERNICUS/S1_GRD", "type": "sar", "prefix": ["S1"], "bands": ["VV", "VH"], "filters_before": [{"instrumentMode": {"eq": "IW"}}, {"transmitterReceiverPolarisation": {"listContains": "VV"}}, {"transmitterReceiverPolarisation": {"listContains": "VH"}}]}, "date_range": {"start_date": "2017-06-01", "end_date": "2017-08-31"}}}, "task_ids": ["ZVYBG6A3AFCQ3EE24P5BLFV3"], "start_time": 1604686895}}